04_Binario_BCD/src/Bin--->BCD/control_double.v
module control_double(
    input  wire clk,
    input  wire rst,
    input  wire init,
    input  wire [3:0] msb,
    input  wire z,
    output reg  done,
    output reg  sh,
    output reg  ld,
    output reg  ldr2,
    output reg  dec
);

 
    localparam IDLE      = 3'b000;
    localparam SHIFT     = 3'b001;
    localparam CHECK_MSB = 3'b010;
    localparam SUMA      = 3'b011;
    localparam DEC_ST    = 3'b100;
    localparam END1      = 3'b101;

    reg [2:0] state, next_state;


    always @(posedge clk or posedge rst) begin
        if (rst)
            state <= IDLE;
        else
            state <= next_state;
    end

    always @(*) begin
        next_state = state;
        case (state)
            IDLE: begin
                if (init)
                    next_state = SHIFT;
            end

            SHIFT: next_state = CHECK_MSB;
            

            CHECK_MSB: begin
    
                if (msb != 0 && z)
                    next_state = SUMA;
                else if (z)
                    next_state = DEC_ST;
                else
                    next_state = END1;
            end

           

            SUMA: begin
                next_state = DEC_ST;
            end

            DEC_ST: begin
                if (!z)
                    next_state = END1;
                else
                    next_state = SHIFT;
            end

            END1: begin
                next_state = IDLE;
            end

            default: next_state = IDLE;
        endcase
    end


    always @(*) begin
     
        done  = 0;
        sh    = 0;
        ld    = 0;
        ldr2  = 0;
        dec   = 0;

        case (state)
            IDLE: begin
                ld   = 1; 
            end

            SHIFT: begin
                sh   = 1; 
            end

            CHECK_MSB: begin
              
            end

            SUMA: begin
                ldr2 = 1; 
            end

            DEC_ST: begin
                dec = 1;  
            end

            END1: begin
                done = 1; 
            end
        endcase
    end

  
`ifdef BENCH
    reg [8*40:1] state_name;
    always @(*) begin
        case (state)
            IDLE      : state_name = "IDLE";
            SHIFT     : state_name = "SHIFT";
            CHECK_MSB : state_name = "CHECK_MSB";
            SUMA      : state_name = "SUMA";
            DEC_ST    : state_name = "DEC_ST";
            END1      : state_name = "END1";
            default   : state_name = "UNKNOWN";
        endcase
    end
`endif

endmodule

04_Binario_BCD/src/Bin--->BCD/contador.v
module contador(
    input  wire clk,
    input  wire ld,      
    input  wire dec,       
    output reg Z   
    
);

  reg [3:0] m;  

  always @(posedge clk) begin
    if (ld) begin    
        m <= 4'd15;       
        Z <= 1'b1;        
    end
    else  
    if (dec && m > 0) begin
        m <= m - 4'd1;    
        Z <= 1'b1;        
      end
      else if(m==0) begin
        Z <= 1'b0;        
      end
    
  end

endmodule

04_Binario_BCD/src/Bin--->BCD/sum.v
module sum (

    input  wire [3:0] A,
    input  wire       bm,
    output reg  [3:0] A_new
    
);
    
    always @(*) begin
        if (bm) begin
            A_new <= A + 4'd3;  
 
        end else begin
            A_new <= 4'd0;        

        end
    end
endmodule

04_Binario_BCD/src/Bin--->BCD/check.v
module check (
    input  [3:0] A,
    input  [3:0] value,
    output reg bm
);
  
    reg [4:0] diff;  
    reg msb;          

    always @(*) begin
        diff = {1'b0, A} - {1'b0, value};  
        msb = diff[4];                   
        if (!msb)
            bm = 1'b1;
        else
            bm = 1'b0;
    end

endmodule

04_Binario_BCD/src/Bin--->BCD/A_reg.v
module A_reg (
    input  wire        clk,
    input  wire [15:0] X,
    input  wire        ldr2,
    input  wire        ld, 
    input  wire        sh,
    input  wire [15:0] A_new,
    output reg  [15:0] resultado
);

    reg [31:0] A = 32'd0;

    always @(negedge clk) begin
        if (ld) begin
  
            A <= {16'd0, X};              
        end 
        else begin
           
            if (sh)
                A <= {A[30:0], 1'b0};

            if (ldr2) begin
                if (A_new[15:12] != 4'd0)
                    A[31:28] <= A_new[15:12];
                else
                    A[31:28] <= A[31:28];

                if (A_new[11:8] != 4'd0)
                    A[27:24] <= A_new[11:8];
                else
                    A[27:24] <= A[27:24];

                if (A_new[7:4] != 4'd0)
                    A[23:20] <= A_new[7:4];
                else
                    A[23:20] <= A[23:20];

                if (A_new[3:0] != 4'd0)
                    A[19:16] <= A_new[3:0];
                else
                    A[19:16] <= A[19:16];
            end
        end

        resultado <= A[31:16];
    end

endmodule

04_Binario_BCD/src/Bin--->BCD/double.v
module double(
    input  wire       clk,
    input  wire       rst,   
    input  wire       init,
    input  wire [15:0] A,
    output wire [15:0] C,
    output wire       done
);

wire w_sh;
wire w_ldr2;
wire w_Z;
wire w_dec;
wire w_ld;
wire [3:0]w_bm;



wire [15:0]  w_A_new;




A_reg A_reg0    (.clk(clk), .ld(w_ld), .sh(w_sh), .ldr2(w_ldr2), .X(A), .A_new(w_A_new), .resultado(C));
check checkm (.A(C[15:12]), .bm(w_bm[3]), .value(4'd5));
check checkc (.A(C[11:8]), .bm(w_bm[2]), .value(4'd5));
check checkd (.A(C[7:4]), .bm(w_bm[1]), .value(4'd5));
check checku (.A(C[3:0]), .bm(w_bm[0]), .value(4'd5));
sum   summ  (.A(C[15:12]), .bm(w_bm[3]),  .A_new(w_A_new[15:12])); 
sum   sumc  (.A(C[11:8]), .bm(w_bm[2]),  .A_new(w_A_new[11:8])); 
sum   sumd  (.A(C[7:4]), .bm(w_bm[1]),  .A_new(w_A_new[7:4]));  
sum   sumu  (.A(C[3:0]), .bm(w_bm[0]),  .A_new(w_A_new[3:0])); 
contador contador0  (.clk(clk), .ld(w_ld),  .dec(w_dec), .Z(w_Z));
control_double control0 (.clk(clk), .rst(rst), .dec(w_dec), .msb (w_bm), .init(init), .z(w_Z), .done(done), .sh(w_sh), .ld(w_ld), .ldr2(w_ldr2));



endmodule

04_Binario_BCD/src/Bin--->BCD/double_TB.v
`timescale 1ns / 1ps

module double_TB;

  
    reg         clk;
    reg         rst;
    reg         init;
    reg  [15:0] A;
    wire [15:0] C;
    wire        done;

 
    double dut (
        .clk(clk),
        .rst(rst),
        .init(init),
        .A(A),
        .C(C),
        .done(done)
    );

  
    initial begin
        clk = 0;
        forever #5 clk = ~clk; 
    end

    initial begin
   
        $dumpfile("double_TB.vcd");
        $dumpvars(0, double_TB);

        rst  = 1;
        init = 0;
        A    = 16'd0;

      
        #20;
        rst = 0;

        A = 16'b1111; 
        #10 init = 1;
        #10 init = 0;

        wait(done);
        #10;
        $display("Tiempo=%0t | A=0x%h | C=0x%h | done=%b", $time, A, C, done);

   
        A = 16'b00100111; 
        #10 init = 1;
        #10 init = 0;

        wait(done);
        #10;
        $display("Tiempo=%0t | A=0x%h | C=0x%h | done=%b", $time, A, C, done);

    
        #50;
        $finish;
    end


    initial begin
        $monitor("T=%0t | clk=%b | rst=%b | init=%b | A=0x%h | C=0x%h | done=%b",
                  $time, clk, rst, init, A, C, done);
    end

endmodule

04_Binario_BCD/src/Bin--->BCD/double_TB.vcd
$date
	Mon Nov 24 02:42:39 2025
$end
$version
	Icarus Verilog
$end
$timescale
	1ps
$end
$scope module double_TB $end
$var wire 1 ! done $end
$var wire 16 " C [15:0] $end
$var reg 16 # A [15:0] $end
$var reg 1 $ clk $end
$var reg 1 % init $end
$var reg 1 & rst $end
$scope module dut $end
$var wire 16 ' A [15:0] $end
$var wire 1 $ clk $end
$var wire 1 % init $end
$var wire 1 & rst $end
$var wire 1 ( w_sh $end
$var wire 1 ) w_ldr2 $end
$var wire 1 * w_ld $end
$var wire 1 + w_dec $end
$var wire 4 , w_bm [3:0] $end
$var wire 1 - w_Z $end
$var wire 16 . w_A_new [15:0] $end
$var wire 1 ! done $end
$var wire 16 / C [15:0] $end
$scope module A_reg0 $end
$var wire 16 0 A_new [15:0] $end
$var wire 16 1 X [15:0] $end
$var wire 1 $ clk $end
$var wire 1 ( sh $end
$var wire 1 ) ldr2 $end
$var wire 1 * ld $end
$var reg 32 2 A [31:0] $end
$var reg 16 3 resultado [15:0] $end
$upscope $end
$scope module checkc $end
$var wire 4 4 A [3:0] $end
$var wire 4 5 value [3:0] $end
$var reg 1 6 bm $end
$var reg 5 7 diff [4:0] $end
$var reg 1 8 msb $end
$upscope $end
$scope module checkd $end
$var wire 4 9 A [3:0] $end
$var wire 4 : value [3:0] $end
$var reg 1 ; bm $end
$var reg 5 < diff [4:0] $end
$var reg 1 = msb $end
$upscope $end
$scope module checkm $end
$var wire 4 > A [3:0] $end
$var wire 4 ? value [3:0] $end
$var reg 1 @ bm $end
$var reg 5 A diff [4:0] $end
$var reg 1 B msb $end
$upscope $end
$scope module checku $end
$var wire 4 C A [3:0] $end
$var wire 4 D value [3:0] $end
$var reg 1 E bm $end
$var reg 5 F diff [4:0] $end
$var reg 1 G msb $end
$upscope $end
$scope module contador0 $end
$var wire 1 $ clk $end
$var wire 1 * ld $end
$var wire 1 + dec $end
$var reg 1 - Z $end
$var reg 4 H m [3:0] $end
$upscope $end
$scope module control0 $end
$var wire 1 $ clk $end
$var wire 1 % init $end
$var wire 4 I msb [3:0] $end
$var wire 1 & rst $end
$var wire 1 - z $end
$var parameter 3 J CHECK_MSB $end
$var parameter 3 K DEC_ST $end
$var parameter 3 L END1 $end
$var parameter 3 M IDLE $end
$var parameter 3 N SHIFT $end
$var parameter 3 O SUMA $end
$var reg 1 + dec $end
$var reg 1 ! done $end
$var reg 1 * ld $end
$var reg 1 ) ldr2 $end
$var reg 3 P next_state [2:0] $end
$var reg 1 ( sh $end
$var reg 3 Q state [2:0] $end
$var reg 320 R state_name [320:1] $end
$upscope $end
$scope module sumc $end
$var wire 4 S A [3:0] $end
$var wire 1 T bm $end
$var reg 4 U A_new [3:0] $end
$upscope $end
$scope module sumd $end
$var wire 4 V A [3:0] $end
$var wire 1 W bm $end
$var reg 4 X A_new [3:0] $end
$upscope $end
$scope module summ $end
$var wire 4 Y A [3:0] $end
$var wire 1 Z bm $end
$var reg 4 [ A_new [3:0] $end
$upscope $end
$scope module sumu $end
$var wire 4 \ A [3:0] $end
$var wire 1 ] bm $end
$var reg 4 ^ A_new [3:0] $end
$upscope $end
$upscope $end
$upscope $end
$enddefinitions $end
$comment Show the parameter values. $end
$dumpall
b11 O
b1 N
b0 M
b101 L
b100 K
b10 J
$end
#0
$dumpvars
b0 ^
0]
b0 \
b0 [
0Z
b0 Y
b0 X
0W
b0 V
b0 U
0T
b0 S
b1001001010001000100110001000101 R
b0 Q
b0 P
b0 I
bx H
1G
b11011 F
0E
b101 D
b0 C
1B
b11011 A
0@
b101 ?
b0 >
1=
b11011 <
0;
b101 :
b0 9
18
b11011 7
06
b101 5
b0 4
b0 3
b0 2
b0 1
b0 0
b0 /
b0 .
x-
b0 ,
0+
1*
0)
0(
b0 '
1&
0%
0$
b0 #
b0 "
0!
$end
#5000
1-
b1111 H
1$
#10000
0$
#15000
1$
#20000
b1111 2
0$
b1111 #
b1111 '
b1111 1
0&
#25000
1$
#30000
b1 P
0$
1%
#35000
1(
0*
b101001101001000010010010100011001010100 R
b10 P
b1 Q
1$
#40000
b11110 2
b10 P
0$
0%
#45000
b10000110100100001000101010000110100101101011111010011010101001101000010 R
0(
b100 P
b10 Q
1$
#50000
0$
#55000
1+
b10001000100010101000011010111110101001101010100 R
b1 P
b100 Q
1$
#60000
0$
#65000
b101001101001000010010010100011001010100 R
1(
0+
b10 P
b1110 H
b1 Q
1$
#70000
b111100 2
0$
#75000
0(
b10000110100100001000101010000110100101101011111010011010101001101000010 R
b100 P
b10 Q
1$
#80000
0$
#85000
b10001000100010101000011010111110101001101010100 R
1+
b1 P
b100 Q
1$
#90000
0$
#95000
1(
0+
b101001101001000010010010100011001010100 R
b10 P
b1101 H
b1 Q
1$
#100000
b1111000 2
0$
#105000
b10000110100100001000101010000110100101101011111010011010101001101000010 R
0(
b100 P
b10 Q
1$
#110000
0$
#115000
1+
b10001000100010101000011010111110101001101010100 R
b1 P
b100 Q
1$
#120000
0$
#125000
b101001101001000010010010100011001010100 R
1(
0+
b10 P
b1100 H
b1 Q
1$
#130000
b11110000 2
0$
#135000
0(
b10000110100100001000101010000110100101101011111010011010101001101000010 R
b100 P
b10 Q
1$
#140000
0$
#145000
b10001000100010101000011010111110101001101010100 R
1+
b1 P
b100 Q
1$
#150000
0$
#155000
1(
0+
b101001101001000010010010100011001010100 R
b10 P
b1011 H
b1 Q
1$
#160000
b111100000 2
0$
#165000
b10000110100100001000101010000110100101101011111010011010101001101000010 R
0(
b100 P
b10 Q
1$
#170000
0$
#175000
1+
b10001000100010101000011010111110101001101010100 R
b1 P
b100 Q
1$
#180000
0$
#185000
b101001101001000010010010100011001010100 R
1(
0+
b10 P
b1010 H
b1 Q
1$
#190000
b1111000000 2
0$
#195000
0(
b10000110100100001000101010000110100101101011111010011010101001101000010 R
b100 P
b10 Q
1$
#200000
0$
#205000
b10001000100010101000011010111110101001101010100 R
1+
b1 P
b100 Q
1$
#210000
0$
#215000
1(
0+
b101001101001000010010010100011001010100 R
b10 P
b1001 H
b1 Q
1$
#220000
b11110000000 2
0$
#225000
b10000110100100001000101010000110100101101011111010011010101001101000010 R
0(
b100 P
b10 Q
1$
#230000
0$
#235000
1+
b10001000100010101000011010111110101001101010100 R
b1 P
b100 Q
1$
#240000
0$
#245000
b101001101001000010010010100011001010100 R
1(
0+
b10 P
b1000 H
b1 Q
1$
#250000
b111100000000 2
0$
#255000
0(
b10000110100100001000101010000110100101101011111010011010101001101000010 R
b100 P
b10 Q
1$
#260000
0$
#265000
b10001000100010101000011010111110101001101010100 R
1+
b1 P
b100 Q
1$
#270000
0$
#275000
1(
0+
b101001101001000010010010100011001010100 R
b10 P
b111 H
b1 Q
1$
#280000
b1111000000000 2
0$
#285000
b10000110100100001000101010000110100101101011111010011010101001101000010 R
0(
b100 P
b10 Q
1$
#290000
0$
#295000
1+
b10001000100010101000011010111110101001101010100 R
b1 P
b100 Q
1$
#300000
0$
#305000
b101001101001000010010010100011001010100 R
1(
0+
b10 P
b110 H
b1 Q
1$
#310000
b11110000000000 2
0$
#315000
0(
b10000110100100001000101010000110100101101011111010011010101001101000010 R
b100 P
b10 Q
1$
#320000
0$
#325000
b10001000100010101000011010111110101001101010100 R
1+
b1 P
b100 Q
1$
#330000
0$
#335000
1(
0+
b101001101001000010010010100011001010100 R
b10 P
b101 H
b1 Q
1$
#340000
b111100000000000 2
0$
#345000
b10000110100100001000101010000110100101101011111010011010101001101000010 R
0(
b100 P
b10 Q
1$
#350000
0$
#355000
1+
b10001000100010101000011010111110101001101010100 R
b1 P
b100 Q
1$
#360000
0$
#365000
b101001101001000010010010100011001010100 R
1(
0+
b10 P
b100 H
b1 Q
1$
#370000
b1111000000000000 2
0$
#375000
0(
b10000110100100001000101010000110100101101011111010011010101001101000010 R
b100 P
b10 Q
1$
#380000
0$
#385000
b10001000100010101000011010111110101001101010100 R
1+
b1 P
b100 Q
1$
#390000
0$
#395000
1(
0+
b101001101001000010010010100011001010100 R
b10 P
b11 H
b1 Q
1$
#400000
b11110000000000000 2
0$
#405000
b10000110100100001000101010000110100101101011111010011010101001101000010 R
0(
b100 P
b10 Q
1$
#410000
b11100 F
b1 \
b1 C
b1 "
b1 /
b1 3
0$
#415000
1+
b10001000100010101000011010111110101001101010100 R
b1 P
b100 Q
1$
#420000
0$
#425000
b101001101001000010010010100011001010100 R
1(
0+
b10 P
b10 H
b1 Q
1$
#430000
b111100000000000000 2
0$
#435000
0(
b10000110100100001000101010000110100101101011111010011010101001101000010 R
b100 P
b10 Q
1$
#440000
b11110 F
b11 \
b11 C
b11 "
b11 /
b11 3
0$
#445000
b10001000100010101000011010111110101001101010100 R
1+
b1 P
b100 Q
1$
#450000
0$
#455000
1(
0+
b101001101001000010010010100011001010100 R
b10 P
b1 H
b1 Q
1$
#460000
b1111000000000000000 2
0$
#465000
b10000110100100001000101010000110100101101011111010011010101001101000010 R
0(
b100 P
b10 Q
1$
#470000
b1010 .
b1010 0
b1010 ^
1]
b11 P
b1 ,
b1 I
1E
0G
b10 F
b111 \
b111 C
b111 "
b111 /
b111 3
0$
#475000
1)
b1010011010101010100110101000001 R
b100 P
b11 Q
1$
#480000
b10101000000000000000 2
0$
#485000
b10001000100010101000011010111110101001101010100 R
1+
0)
b1 P
b100 Q
1$
#490000
b1101 .
b1101 0
b1101 ^
b101 F
b1010 \
b1010 C
b1010 "
b1010 /
b1010 3
0$
#495000
1(
0+
b101001101001000010010010100011001010100 R
b10 P
b0 H
b1 Q
1$
#500000
b101010000000000000000 2
0$
#505000
b10000110100100001000101010000110100101101011111010011010101001101000010 R
0(
b101 P
0-
b10 Q
1$
#510000
b1000 .
b1000 0
b1000 ^
b0 F
b11100 <
b101 \
b1 V
b101 C
b1 9
b10101 "
b10101 /
b10101 3
0$
#515000
1!
b1000101010011100100010000110001 R
b0 P
b101 Q
1$
#520000
0$
#525000
b1001001010001000100110001000101 R
1*
0!
b0 Q
1$
b100111 #
b100111 '
b100111 1
#530000
b100111 2
0$
#535000
1(
0*
b101001101001000010010010100011001010100 R
1-
b1111 H
b1 Q
b10 P
1$
1%
#540000
b0 .
b0 0
b0 ^
0]
b10 P
b0 ,
b0 I
0E
1G
b11011 F
b11011 <
b0 \
b0 V
b0 C
b0 9
b0 "
b0 /
b0 3
b1001110 2
0$
#545000
b10000110100100001000101010000110100101101011111010011010101001101000010 R
0(
b10 Q
b100 P
1$
0%
#550000
0$
#555000
1+
b10001000100010101000011010111110101001101010100 R
b1 P
b100 Q
1$
#560000
0$
#565000
b101001101001000010010010100011001010100 R
1(
0+
b10 P
b1110 H
b1 Q
1$
#570000
b10011100 2
0$
#575000
0(
b10000110100100001000101010000110100101101011111010011010101001101000010 R
b100 P
b10 Q
1$
#580000
0$
#585000
b10001000100010101000011010111110101001101010100 R
1+
b1 P
b100 Q
1$
#590000
0$
#595000
1(
0+
b101001101001000010010010100011001010100 R
b10 P
b1101 H
b1 Q
1$
#600000
b100111000 2
0$
#605000
b10000110100100001000101010000110100101101011111010011010101001101000010 R
0(
b100 P
b10 Q
1$
#610000
0$
#615000
1+
b10001000100010101000011010111110101001101010100 R
b1 P
b100 Q
1$
#620000
0$
#625000
b101001101001000010010010100011001010100 R
1(
0+
b10 P
b1100 H
b1 Q
1$
#630000
b1001110000 2
0$
#635000
0(
b10000110100100001000101010000110100101101011111010011010101001101000010 R
b100 P
b10 Q
1$
#640000
0$
#645000
b10001000100010101000011010111110101001101010100 R
1+
b1 P
b100 Q
1$
#650000
0$
#655000
1(
0+
b101001101001000010010010100011001010100 R
b10 P
b1011 H
b1 Q
1$
#660000
b10011100000 2
0$
#665000
b10000110100100001000101010000110100101101011111010011010101001101000010 R
0(
b100 P
b10 Q
1$
#670000
0$
#675000
1+
b10001000100010101000011010111110101001101010100 R
b1 P
b100 Q
1$
#680000
0$
#685000
b101001101001000010010010100011001010100 R
1(
0+
b10 P
b1010 H
b1 Q
1$
#690000
b100111000000 2
0$
#695000
0(
b10000110100100001000101010000110100101101011111010011010101001101000010 R
b100 P
b10 Q
1$
#700000
0$
#705000
b10001000100010101000011010111110101001101010100 R
1+
b1 P
b100 Q
1$
#710000
0$
#715000
1(
0+
b101001101001000010010010100011001010100 R
b10 P
b1001 H
b1 Q
1$
#720000
b1001110000000 2
0$
#725000
b10000110100100001000101010000110100101101011111010011010101001101000010 R
0(
b100 P
b10 Q
1$
#730000
0$
#735000
1+
b10001000100010101000011010111110101001101010100 R
b1 P
b100 Q
1$
#740000
0$
#745000
b101001101001000010010010100011001010100 R
1(
0+
b10 P
b1000 H
b1 Q
1$
#750000
b10011100000000 2
0$
#755000
0(
b10000110100100001000101010000110100101101011111010011010101001101000010 R
b100 P
b10 Q
1$
#760000
0$
#765000
b10001000100010101000011010111110101001101010100 R
1+
b1 P
b100 Q
1$
#770000
0$
#775000
1(
0+
b101001101001000010010010100011001010100 R
b10 P
b111 H
b1 Q
1$
#780000
b100111000000000 2
0$
#785000
b10000110100100001000101010000110100101101011111010011010101001101000010 R
0(
b100 P
b10 Q
1$
#790000
0$
#795000
1+
b10001000100010101000011010111110101001101010100 R
b1 P
b100 Q
1$
#800000
0$
#805000
b101001101001000010010010100011001010100 R
1(
0+
b10 P
b110 H
b1 Q
1$
#810000
b1001110000000000 2
0$
#815000
0(
b10000110100100001000101010000110100101101011111010011010101001101000010 R
b100 P
b10 Q
1$
#820000
0$
#825000
b10001000100010101000011010111110101001101010100 R
1+
b1 P
b100 Q
1$
#830000
0$
#835000
1(
0+
b101001101001000010010010100011001010100 R
b10 P
b101 H
b1 Q
1$
#840000
b10011100000000000 2
0$
#845000
b10000110100100001000101010000110100101101011111010011010101001101000010 R
0(
b100 P
b10 Q
1$
#850000
b11100 F
b1 \
b1 C
b1 "
b1 /
b1 3
0$
#855000
1+
b10001000100010101000011010111110101001101010100 R
b1 P
b100 Q
1$
#860000
0$
#865000
b101001101001000010010010100011001010100 R
1(
0+
b10 P
b100 H
b1 Q
1$
#870000
b100111000000000000 2
0$
#875000
0(
b10000110100100001000101010000110100101101011111010011010101001101000010 R
b100 P
b10 Q
1$
#880000
b11101 F
b10 \
b10 C
b10 "
b10 /
b10 3
0$
#885000
b10001000100010101000011010111110101001101010100 R
1+
b1 P
b100 Q
1$
#890000
0$
#895000
1(
0+
b101001101001000010010010100011001010100 R
b10 P
b11 H
b1 Q
1$
#900000
b1001110000000000000 2
0$
#905000
b10000110100100001000101010000110100101101011111010011010101001101000010 R
0(
b100 P
b10 Q
1$
#910000
b11111 F
b100 \
b100 C
b100 "
b100 /
b100 3
0$
#915000
1+
b10001000100010101000011010111110101001101010100 R
b1 P
b100 Q
1$
#920000
0$
#925000
b101001101001000010010010100011001010100 R
1(
0+
b10 P
b10 H
b1 Q
1$
#930000
b10011100000000000000 2
0$
#935000
0(
b10000110100100001000101010000110100101101011111010011010101001101000010 R
b100 P
b10 Q
1$
#940000
b1100 .
b1100 0
b1100 ^
1]
b11 P
b1 ,
b1 I
1E
0G
b100 F
b1001 \
b1001 C
b1001 "
b1001 /
b1001 3
0$
#945000
b1010011010101010100110101000001 R
1)
b100 P
b11 Q
1$
#950000
b11001100000000000000 2
0$
#955000
1+
0)
b10001000100010101000011010111110101001101010100 R
b1 P
b100 Q
1$
#960000
b1111 .
b1111 0
b1111 ^
b111 F
b1100 \
b1100 C
b1100 "
b1100 /
b1100 3
0$
#965000
b101001101001000010010010100011001010100 R
1(
0+
b10 P
b1 H
b1 Q
1$
#970000
b110011000000000000000 2
0$
#975000
0(
b10000110100100001000101010000110100101101011111010011010101001101000010 R
b11 P
b10 Q
1$
#980000
b1100 .
b1100 0
b1100 ^
b100 F
b11100 <
b1001 \
b1 V
b1001 C
b1 9
b11001 "
b11001 /
b11001 3
0$
#985000
b1010011010101010100110101000001 R
1)
b100 P
b11 Q
1$
#990000
b111001000000000000000 2
0$
#995000
1+
0)
b10001000100010101000011010111110101001101010100 R
b1 P
b100 Q
1$
#1000000
b1111 .
b1111 0
b1111 ^
b111 F
b1100 \
b1100 C
b11100 "
b11100 /
b11100 3
0$
#1005000
b101001101001000010010010100011001010100 R
1(
0+
b10 P
b0 H
b1 Q
1$
#1010000
b1110010000000000000000 2
0$
#1015000
0(
b10000110100100001000101010000110100101101011111010011010101001101000010 R
b101 P
0-
b10 Q
1$
#1020000
b1100 .
b1100 0
b1100 ^
b100 F
b11110 <
b1001 \
b11 V
b1001 C
b11 9
b111001 "
b111001 /
b111001 3
0$
#1025000
b1000101010011100100010000110001 R
1!
b0 P
b101 Q
1$
#1030000
0$
#1035000
1*
0!
b1001001010001000100110001000101 R
b0 Q
1$
#1040000
b100111 2
0$
#1045000
1-
b1111 H
1$
#1050000
b0 .
b0 0
b0 ^
0]
b0 ,
b0 I
0E
1G
b11011 F
b11011 <
b0 \
b0 V
b0 C
b0 9
b0 "
b0 /
b0 3
0$
